LICENSE
README.rst
setup.cfg
setup.py
json_processor/__init__.py
json_processor/__main__.py
json_processor/version.py
json_processor.egg-info/PKG-INFO
json_processor.egg-info/SOURCES.txt
json_processor.egg-info/dependency_links.txt
json_processor.egg-info/entry_points.txt
json_processor.egg-info/requires.txt
json_processor.egg-info/top_level.txt
json_processor/test/__init__.py
json_processor/test/array_test.py
json_processor/test/base_test.py
json_processor/test/cast_test.py
json_processor/test/import_test.py
json_processor/test/list_test.py
json_processor/test/runtests.py